py_project_utils_xethhung12/__init__.py
py_project_utils_xethhung12/__main__.py
py_project_utils_xethhung12/_module_project_creation.py
py_project_utils_xethhung12/_cmd/run.py
py_project_utils_xethhung12/data/.gitignore
py_project_utils_xethhung12/data/LICENSE
py_project_utils_xethhung12/data/README.md
py_project_utils_xethhung12/data/build-and-deploy.sh
py_project_utils_xethhung12/data/build.sh
py_project_utils_xethhung12/data/dev-requirements.txt
py_project_utils_xethhung12/data/install-dependencies.sh
py_project_utils_xethhung12/data/pyproject.toml
py_project_utils_xethhung12/data/requirements.txt
py_project_utils_xethhung12/data/src$___project_name___$__init__.py
py_project_utils_xethhung12/data/src$___project_name___$__main__.py
py_project_utils_xethhung12/data/src$___project_name___$_cmd$run.py
py_project_utils_xethhung12/data/src$___project_name___$_module_helloworld.py
py_project_utils_xethhung12-0.1.5.dist-info/METADATA
py_project_utils_xethhung12-0.1.5.dist-info/WHEEL
py_project_utils_xethhung12-0.1.5.dist-info/entry_points.txt
py_project_utils_xethhung12-0.1.5.dist-info/licenses/LICENSE
py_project_utils_xethhung12-0.1.5.dist-info/RECORD
